[
  {
    "id": "17525TR179A",
    "name": "Шина   17.5-25 TR179A",
    "price": 4700,
    "size": "17.5-25",
    "stock": 89,
    "modal_name": "",
    "img": "https://shop.liftnet.ru/tr-lift/dealer.work//pic/00000030407.jpg",
    "options": [
      [
        "Модель:",
        "Камера"
      ],
      [
        "Типоразмер:",
        "17.5-25"
      ],
      [
        "Исполнение:",
        "Камера"
      ],
      [
        "Вес (кг):",
        "13.2"
      ],
      [
        "Страна производитель:",
        "КИТАЙ"
      ]
    ]
  },
  {
    "id": "23525TR179A",
    "name": "Шина   23.5-25 TR179A",
    "price": 7518,
    "size": "23.5-25",
    "stock": 145,
    "modal_name": "",
    "img": "https://shop.liftnet.ru/tr-lift/dealer.work//pic/00000028319.jpg",
    "options": [
      [
        "Модель:",
        "Камера"
      ],
      [
        "Типоразмер:",
        "23.5-25"
      ],
      [
        "Исполнение:",
        "Камера"
      ],
      [
        "Вес (кг):",
        "21.7"
      ],
      [
        "Страна производитель:",
        "КИТАЙ"
      ]
    ]
  }
]